saliency_detector/__init__.py
saliency_detector/joint_main.py
saliency_detector/joint_solver.py
saliency_detector/main.py
saliency_detector/poolnet.py
saliency_detector/saliency_detector.py
saliency_detector/solver.py
saliency_detector/dataset/__init__.py
saliency_detector/dataset/dataset.py
saliency_detector/dataset/joint_dataset.py
saliency_detector/networks/__init__.py
saliency_detector/networks/deeplab_resnet.py
saliency_detector/networks/joint_poolnet.py
saliency_detector/networks/poolnet.py
saliency_detector/networks/vgg.py
saliency_detector-0.2.5.dist-info/LICENSE
saliency_detector-0.2.5.dist-info/METADATA
saliency_detector-0.2.5.dist-info/WHEEL
saliency_detector-0.2.5.dist-info/top_level.txt
saliency_detector-0.2.5.dist-info/RECORD
