Metadata-Version: 2.1
Name: saliency-detector
Version: 0.2.5
Summary: Pretrained Poolnet Saliency Detector for Inference
Home-page: https://github.com/balast/saliency_detector
Author: Adam Dudley Lewis
Author-email: balast@users.noreply.github.com
License: GNU General Public License v3
Keywords: saliency_detector
Platform: UNKNOWN
Classifier: Development Status :: 2 - Pre-Alpha
Classifier: Intended Audience :: Developers
Classifier: License :: OSI Approved :: GNU General Public License v3 (GPLv3)
Classifier: Natural Language :: English
Classifier: Programming Language :: Python :: 3
Classifier: Programming Language :: Python :: 3.5
Classifier: Programming Language :: Python :: 3.6
Classifier: Programming Language :: Python :: 3.7
Classifier: Programming Language :: Python :: 3.8
Classifier: Operating System :: OS Independent
Requires-Python: >=3.5
Requires-Dist: torch
Requires-Dist: torchvision
Requires-Dist: scipy
Requires-Dist: pillow
Requires-Dist: opencv-python
